sed_scores_eval/__init__.py
sed_scores_eval/base_modules/__init__.py
sed_scores_eval/base_modules/bootstrap.py
sed_scores_eval/base_modules/curves.py
sed_scores_eval/base_modules/cy_detection.cpython-311-darwin.so
sed_scores_eval/base_modules/cy_detection.pyx
sed_scores_eval/base_modules/cy_medfilt.cpython-311-darwin.so
sed_scores_eval/base_modules/cy_medfilt.pyx
sed_scores_eval/base_modules/detection.py
sed_scores_eval/base_modules/error_rate.py
sed_scores_eval/base_modules/ground_truth.py
sed_scores_eval/base_modules/io.py
sed_scores_eval/base_modules/postprocessing.py
sed_scores_eval/base_modules/precision_recall.py
sed_scores_eval/base_modules/roc.py
sed_scores_eval/base_modules/scores.py
sed_scores_eval/base_modules/statistics.py
sed_scores_eval/clip_based/__init__.py
sed_scores_eval/clip_based/error_rate.py
sed_scores_eval/clip_based/intermediate_statistics.py
sed_scores_eval/clip_based/precision_recall.py
sed_scores_eval/clip_based/reference.py
sed_scores_eval/clip_based/roc.py
sed_scores_eval/collar_based/__init__.py
sed_scores_eval/collar_based/error_rate.py
sed_scores_eval/collar_based/intermediate_statistics.py
sed_scores_eval/collar_based/precision_recall.py
sed_scores_eval/collar_based/reference.py
sed_scores_eval/intersection_based/__init__.py
sed_scores_eval/intersection_based/error_rate.py
sed_scores_eval/intersection_based/intermediate_statistics.py
sed_scores_eval/intersection_based/pipsds.py
sed_scores_eval/intersection_based/precision_recall.py
sed_scores_eval/intersection_based/psds.py
sed_scores_eval/intersection_based/reference.py
sed_scores_eval/segment_based/__init__.py
sed_scores_eval/segment_based/error_rate.py
sed_scores_eval/segment_based/intermediate_statistics.py
sed_scores_eval/segment_based/precision_recall.py
sed_scores_eval/segment_based/reference.py
sed_scores_eval/segment_based/roc.py
sed_scores_eval/utils/__init__.py
sed_scores_eval/utils/array_ops.py
sed_scores_eval/utils/nested.py
sed_scores_eval/utils/parallel.py
sed_scores_eval-0.0.4.dist-info/LICENSE
sed_scores_eval-0.0.4.dist-info/METADATA
sed_scores_eval-0.0.4.dist-info/WHEEL
sed_scores_eval-0.0.4.dist-info/top_level.txt
sed_scores_eval-0.0.4.dist-info/RECORD
