Metadata-Version: 2.1
Name: sed_scores_eval
Version: 0.0.4
Summary: (Threshold-Independent) Evaluation of Sound Event Detection Scores
Home-page: https://github.com/fgnt/sed_scores_eval
Author: Department of Communications Engineering, Paderborn University
Author-email: sek@nt.upb.de
License: MIT
Keywords: sound recognition evaluation from classification scores
Classifier: Development Status :: 3 - Alpha
Classifier: Intended Audience :: Developers
Classifier: Topic :: Software Development :: Build Tools
Classifier: License :: OSI Approved :: MIT License
Classifier: Programming Language :: Python :: 3.7
Classifier: Programming Language :: Python :: 3.8
Classifier: Programming Language :: Python :: 3.9
Classifier: Programming Language :: Python :: 3.10
Classifier: Programming Language :: Python :: 3.11
License-File: LICENSE
Requires-Dist: numpy
Requires-Dist: pandas
Requires-Dist: scipy
Requires-Dist: pathlib
Requires-Dist: lazy-dataset
Requires-Dist: einops
Requires-Dist: sed-eval
Requires-Dist: Cython
Provides-Extra: dev
Requires-Dist: check-manifest ; extra == 'dev'
Provides-Extra: test
Requires-Dist: coverage ; extra == 'test'
Requires-Dist: jupyter ; extra == 'test'
Requires-Dist: matplotlib ; extra == 'test'
